LICENSE
README.md
setup.py
LLM4TS/__init__.py
LLM4TS/agents.py
LLM4TS/events.py
LLM4TS/llm_prompt.py
LLM4TS/utilities.py
LLM4TS.egg-info/PKG-INFO
LLM4TS.egg-info/SOURCES.txt
LLM4TS.egg-info/dependency_links.txt
LLM4TS.egg-info/entry_points.txt
LLM4TS.egg-info/requires.txt
LLM4TS.egg-info/top_level.txt